kitchenai_rag_simple_bento/__init__.py
kitchenai_rag_simple_bento/__version__.py
kitchenai_rag_simple_bento/admin.py
kitchenai_rag_simple_bento/apps.py
kitchenai_rag_simple_bento/kitchen.py
kitchenai_rag_simple_bento/urls.py
kitchenai_rag_simple_bento/views.py
kitchenai_rag_simple_bento/migrations/__init__.py
kitchenai_rag_simple_bento/templates/kitchenai_rag_simple_bento/pages/home.html
kitchenai_rag_simple_bento/templates/kitchenai_rag_simple_bento/pages/settings.html
kitchenai_rag_simple_bento/tests/__init__.py
kitchenai_rag_simple_bento/tests/settings.py
kitchenai_rag_simple_bento/tests/test_django.py
kitchenai_rag_simple_bento/tests/test_routes.py
kitchenai_rag_simple_bento-0.1.10.dist-info/METADATA
kitchenai_rag_simple_bento-0.1.10.dist-info/WHEEL
kitchenai_rag_simple_bento-0.1.10.dist-info/entry_points.txt
kitchenai_rag_simple_bento-0.1.10.dist-info/licenses/LICENSE
kitchenai_rag_simple_bento-0.1.10.dist-info/RECORD
