Metadata-Version: 2.4
Name: kitchenai_rag_simple_bento
Version: 0.1.10
Author-email: epuerta <esteban_puerta@rhinosearch.io>
License-File: LICENSE
Classifier: Programming Language :: Python :: 3 :: Only
Classifier: Programming Language :: Python :: 3.11
Classifier: Programming Language :: Python :: 3.12
Requires-Python: >=3.11
Requires-Dist: boto3
Requires-Dist: chromadb
Requires-Dist: django
Requires-Dist: djp
Requires-Dist: kitchenai-llama
Requires-Dist: llama-index
Requires-Dist: llama-index-llms-litellm
Requires-Dist: llama-index-vector-stores-chroma
